{"State.8dfc234d-c0b7-4df1-bc24-12a49721b62c": {"id": "8dfc234d-c0b7-4df1-bc24-12a49721b62c", "created_at": "2024-06-05 06:35:10.154657", "name": "California", "updated_at": "2024-06-05 06:35:10.154737", "__class__": "State"}, "State.a1866d47-e569-44d2-9688-09415c546b7b": {"id": "a1866d47-e569-44d2-9688-09415c546b7b", "created_at": "2024-06-05 06:35:28.968001", "name": "Arizona", "updated_at": "2024-06-05 06:35:28.968062", "__class__": "State"}, "Place.14eceb70-a1bb-4c7a-9033-b30c26050b56": {"id": "14eceb70-a1bb-4c7a-9033-b30c26050b56", "created_at": "2024-06-05 06:49:56.092680", "city id": "0001", "user id": "0001", "name": "My_little_house", "number rooms": 4, "number bathrooms": 2, "max guest": 10, "price by night": 300, "latitude": 37.773972, "longitude": -122.431297, "updated_at": "2024-06-05 06:49:56.092782", "__class__": "Place"}}